LICENSE
MANIFEST.in
newpy.py
setup.py
newpy.egg-info/PKG-INFO
newpy.egg-info/SOURCES.txt
newpy.egg-info/dependency_links.txt
newpy.egg-info/top_level.txt
resources/Logger.py
resources/README.md
resources/__init__.py
resources/py_skeleton.py
resources/py_skeleton_with_logger.py
resources/setup.py