Metadata-Version: 1.1
Name: newpy
Version: 1.1.16
Summary: Quickly and easily create a new python project
Home-page: https://bitbucket.org/edwardonsoftware/newpy
Author: Edward
Author-email: edwardprentice@gmail.com
License: MIT
Download-URL: https://pypi.python.org/pypi/newpy
Keywords: tutorial new example skeleton
Platform: UNKNOWN
Classifier: Development Status :: 3 - Alpha
Classifier: Intended Audience :: Developers
Classifier: Topic :: Software Development :: Build Tools
Classifier: License :: OSI Approved :: MIT License
Classifier: Operating System :: MacOS :: MacOS X
Classifier: Operating System :: Microsoft :: Windows
Classifier: Operating System :: POSIX
Classifier: Programming Language :: Python :: 3
Classifier: Programming Language :: Python :: 3.0
Classifier: Programming Language :: Python :: 3.1
Classifier: Programming Language :: Python :: 3.2
Classifier: Programming Language :: Python :: 3.3
Classifier: Programming Language :: Python :: 3.4
Classifier: Programming Language :: Python :: 3 :: Only
